bandcamp_dl/__init__.py
bandcamp_dl/__main__.py
bandcamp_dl/bandcamp.py
bandcamp_dl/bandcampdownloader.py
bandcamp_dl/bandcampjson.py
bandcamp_dl/config.py
bandcamp_downloader-0.0.17.dist-info/licenses/AUTHORS.rst
bandcamp_downloader-0.0.17.dist-info/licenses/LICENSE
bandcamp_downloader-0.0.17.dist-info/METADATA
bandcamp_downloader-0.0.17.dist-info/WHEEL
bandcamp_downloader-0.0.17.dist-info/entry_points.txt
bandcamp_downloader-0.0.17.dist-info/top_level.txt
bandcamp_downloader-0.0.17.dist-info/RECORD
