Metadata-Version: 2.4
Name: bandcamp-downloader
Version: 0.0.17
Summary: bandcamp-dl downloads albums and tracks from Bandcamp for you
Author-email: Iheanyi Ekechukwu <iekechukwu@gmail.com>, Anthony Forsberg <forsberganthony@yahoo.com>
Project-URL: Documentation, https://github.com/iheanyi/bandcamp-dl/blob/master/README.rst
Project-URL: Source, https://github.com/iheanyi/bandcamp-dl
Project-URL: Tracker, https://github.com/iheanyi/bandcamp-dl/issues
Classifier: Development Status :: 4 - Beta
Classifier: Intended Audience :: End Users/Desktop
Classifier: Topic :: Multimedia :: Sound/Audio
Classifier: License :: Public Domain
Classifier: Programming Language :: Python :: 3.4
Requires-Python: >=3.4
License-File: LICENSE
License-File: AUTHORS.rst
Requires-Dist: beautifulsoup4>=4.13.0b2
Requires-Dist: demjson3>=3.0.6
Requires-Dist: mutagen>=1.47.0
Requires-Dist: requests>=2.32.3
Requires-Dist: unicode-slugify>=0.1.5
Requires-Dist: urllib3>=2.2.2
Requires-Dist: toml; python_version < "3.11"
Dynamic: license-file
